panzi_inotify/__init__.py
panzi_inotify/__main__.py
panzi_inotify/inotify.py
panzi_inotify/py.typed
panzi_inotify-1.0.2.dist-info/licenses/LICENSE.txt
panzi_inotify-1.0.2.dist-info/METADATA
panzi_inotify-1.0.2.dist-info/WHEEL
panzi_inotify-1.0.2.dist-info/top_level.txt
panzi_inotify-1.0.2.dist-info/RECORD
