Metadata-Version: 2.4
Name: panzi_inotify
Version: 1.0.2
Summary: Simple Linux inotify bindings for Python, including OSErrors.
License-Expression: MPL-2.0
Project-URL: Homepage, https://pypi.org/project/panzi_inotify/
Project-URL: Repository, https://github.com/panzi/panzi-inotify/
Project-URL: Issue Tracker, https://github.com/panzi/panzi-inotify/issues
Keywords: inotify,linux
Classifier: Operating System :: POSIX :: Linux
Classifier: Programming Language :: Python :: 3
Classifier: Programming Language :: Python :: 3.10
Classifier: Topic :: System :: Filesystems
Requires-Python: >=3.10
License-File: LICENSE.txt
Dynamic: license-file
